skelescope/__init__.py
skelescope/static/widget.css
skelescope/static/widget.js
skelescope-0.0.8.dist-info/LICENSE
skelescope-0.0.8.dist-info/METADATA
skelescope-0.0.8.dist-info/WHEEL
skelescope-0.0.8.dist-info/RECORD
