Metadata-Version: 2.1
Name: skelescope
Version: 0.0.8
Summary: 
License: MIT
Author: Philipp Harth
Author-email: harth@zib.de
Requires-Python: >=3.9,<4.0
Classifier: License :: OSI Approved :: MIT License
Classifier: Programming Language :: Python :: 3
Classifier: Programming Language :: Python :: 3.9
Classifier: Programming Language :: Python :: 3.10
Classifier: Programming Language :: Python :: 3.11
Classifier: Programming Language :: Python :: 3.12
Requires-Dist: anywidget (>=0.9.6,<0.10.0)
Requires-Dist: jupyterlab (>=4.1.5,<5.0.0)
Requires-Dist: navis (>=1.6.0,<2.0.0)
Requires-Dist: watchfiles (>=0.21.0,<0.22.0)
